langgraph_api/base/api/__init__.py
langgraph_api/base/api/assistants.py
langgraph_api/base/api/meta.py
langgraph_api/base/api/openapi.py
langgraph_api/base/api/runs.py
langgraph_api/base/api/store.py
langgraph_api/base/api/threads.py
langgraph_api/base/auth/__init__.py
langgraph_api/base/auth/langsmith/__init__.py
langgraph_api/base/auth/langsmith/backend.py
langgraph_api/base/auth/langsmith/client.py
langgraph_api/base/auth/middleware.py
langgraph_api/base/auth/noop.py
langgraph_api/base/config.py
langgraph_api/base/cron_scheduler.py
langgraph_api/base/http.py
langgraph_api/base/js.py
langgraph_api/base/lifespan.py
langgraph_api/base/metadata.py
langgraph_api/base/models/__init__.py
langgraph_api/base/models/run.py
langgraph_api/base/openapi.json
langgraph_api/base/patch.py
langgraph_api/base/queue.py
langgraph_api/base/shared/__init__.py
langgraph_api/base/shared/asyncio.py
langgraph_api/base/shared/errors.py
langgraph_api/base/shared/graph.py
langgraph_api/base/shared/http_logger.py
langgraph_api/base/shared/logging.py
langgraph_api/base/shared/route.py
langgraph_api/base/shared/schema.py
langgraph_api/base/shared/serde.py
langgraph_api/base/shared/sse.py
langgraph_api/base/shared/state.py
langgraph_api/base/shared/stream.py
langgraph_api/base/shared/utils.py
langgraph_api/base/shared/validation.py
langgraph_api/base/shared/webhooks.py
langgraph_api/cli.py
langgraph_api/license/middleware.py
langgraph_api/license/validation.py
langgraph_api/server.py
langgraph_api/storage/__init__.py
langgraph_api/storage/base/.ruff_cache/.gitignore
langgraph_api/storage/base/.ruff_cache/CACHEDIR.TAG
langgraph_api/storage/checkpoint.py
langgraph_api/storage/database.py
langgraph_api/storage/ops.py
langgraph_api/storage/queue.py
langgraph_api/storage/retry.py
langgraph_api/storage/store.py
langgraph_api/storage/ttl_dict.py
langgraph_api_inmem-0.0.2.dist-info/METADATA
langgraph_api_inmem-0.0.2.dist-info/WHEEL
langgraph_api_inmem-0.0.2.dist-info/entry_points.txt
langgraph_api_inmem-0.0.2.dist-info/RECORD
